ttlstore/__init__.py
ttlstore/ttlstore.py
ttlstore-0.1.0.dist-info/LICENSE
ttlstore-0.1.0.dist-info/METADATA
ttlstore-0.1.0.dist-info/WHEEL
ttlstore-0.1.0.dist-info/top_level.txt
ttlstore-0.1.0.dist-info/RECORD
