Metadata-Version: 2.1
Name: ttlstore
Version: 0.1.0
Summary: ttlstore provides dict like functionality that automatically removes the element from memory after ttl seconds
Home-page: https://github.com/foxpass/ttlstore
Author: grk-it
License: MIT
Classifier: Intended Audience :: Developers
Classifier: License :: OSI Approved :: Apache Software License
Classifier: Programming Language :: Python
Classifier: Programming Language :: Python :: 3
Classifier: Programming Language :: Python :: 3.6
Classifier: Programming Language :: Python :: 3.7
Classifier: Programming Language :: Python :: 3.8
Classifier: Programming Language :: Python :: 3.9
Classifier: Operating System :: OS Independent
Classifier: Topic :: Software Development :: Libraries
License-File: LICENSE
